pytestifypro/__init__.py
pytestifypro/client/api_client.py
pytestifypro/comparer/__init__.py
pytestifypro/comparer/json_comparer.py
pytestifypro/config/config.py
pytestifypro/config/config.yaml
pytestifypro/config/priority_map.yaml
pytestifypro/config/schema_config.yaml
pytestifypro/config/wiremock_config.yaml
pytestifypro/data/__init__.py
pytestifypro/data/data_loader.py
pytestifypro/managers/__init__.py
pytestifypro/managers/priority_manager.py
pytestifypro/reporters/__init__.py
pytestifypro/reporters/difference_reporter.py
pytestifypro/tests/__init__.py
pytestifypro/tests/conftest.py
pytestifypro/tests/sample_test.py
pytestifypro/tests/test_sample_upi_tests.py
pytestifypro/tests/test_utils.py
pytestifypro/utils/__init__.py
pytestifypro/utils/allure_reporter.py
pytestifypro/utils/assertions.py
pytestifypro/utils/check_docker.py
pytestifypro/utils/response_validator.py
pytestifypro/utils/utils.py
pytestifypro-0.1.1.dist-info/LICENSE
pytestifypro-0.1.1.dist-info/METADATA
pytestifypro-0.1.1.dist-info/WHEEL
pytestifypro-0.1.1.dist-info/entry_points.txt
pytestifypro-0.1.1.dist-info/RECORD
