Metadata-Version: 2.1
Name: pytestifypro
Version: 0.1.1
Summary: Python testing framework that enhances pytest by offering utility functions and streamlined configurations. It simplifies writing, executing, and managing tests, making it easier to achieve robust and reliable testing outcomes.
License: MIT
Author: Javed Ansari
Author-email: qabyjavedansari@gmail.com
Requires-Python: >=3.12,<4.0
Classifier: License :: OSI Approved :: MIT License
Classifier: Programming Language :: Python :: 3
Classifier: Programming Language :: Python :: 3.12
Requires-Dist: allure-pytest (>=2.13.5,<3.0.0)
Requires-Dist: allure-python-commons (>=2.13.5,<3.0.0)
Requires-Dist: jsonschema (>=4.23.0,<5.0.0)
Requires-Dist: pytest (>=8.3.2,<9.0.0)
Requires-Dist: pytest-mock (>=3.14.0,<4.0.0)
Requires-Dist: pyyaml (>=6.0.2,<7.0.0)
Requires-Dist: requests (>=2.32.3,<3.0.0)
